{
  "openapi": "3.0.0",
  "info": {
    "title": "Legacy Insurance API V1",
    "version": "1.0.0",
    "description": "Legacy API for life insurance and ILP products"
  },
  "paths": {
    "/api/v1/policy/{id}": {
      "get": {
        "operationId": "getPolicy_v1",
        "parameters": [
          {
            "name": "id",
            "in": "path",
            "required": true,
            "schema": {"type": "string"}
          }
        ],
        "responses": {
          "200": {
            "description": "Policy details",
            "content": {
              "application/json": {
                "schema": {
                  "type": "object",
                  "properties": {
                    "policy_num": {"type": "string"},
                    "policy_status": {"type": "string"},
                    "policy_details": {
                      "type": "object",
                      "properties": {
                        "type": {"type": "string"},
                        "premium_amount": {"type": "number"}
                      }
                    }
                  }
                }
              }
            }
          }
        }
      }
    },
    "/api/v1/policy": {
      "get": {
        "operationId": "getPolicyByParam",
        "parameters": [
          {
            "name": "policy_id",
            "in": "query",
            "required": true,
            "schema": {"type": "string"}
          }
        ],
        "responses": {
          "200": {
            "description": "Policy details",
            "content": {
              "application/json": {
                "schema": {
                  "type": "object",
                  "properties": {
                    "policy_num": {"type": "string"},
                    "policy_status": {"type": "string"}
                  }
                }
              }
            }
          }
        }
      }
    },
    "/api/v1/customer/{customerId}": {
      "get": {
        "operationId": "getCustomer_v1",
        "parameters": [
          {
            "name": "customerId",
            "in": "path",
            "required": true,
            "schema": {"type": "string"}
          }
        ],
        "responses": {
          "200": {
            "description": "Customer details",
            "content": {
              "application/json": {
                "schema": {
                  "type": "object",
                  "properties": {
                    "first_name": {"type": "string"},
                    "last_name": {"type": "string"},
                    "customer_age": {"type": "integer"},
                    "email_address": {"type": "string"}
                  }
                }
              }
            }
          }
        }
      }
    },
    "/api/v1/coverage": {
      "get": {
        "operationId": "getCoverage_v1",
        "parameters": [
          {
            "name": "policy_id",
            "in": "query",
            "required": true,
            "schema": {"type": "string"}
          }
        ],
        "responses": {
          "200": {
            "description": "Coverage details",
            "content": {
              "application/json": {
                "schema": {
                  "type": "object",
                  "properties": {
                    "amount": {"type": "number"},
                    "type": {"type": "string"}
                  }
                }
              }
            }
          }
        }
      }
    },
    "/api/v1/coverage/{id}": {
      "get": {
        "operationId": "getCoverageById_v1",
        "parameters": [
          {
            "name": "id",
            "in": "path",
            "required": true,
            "schema": {"type": "string"}
          }
        ],
        "responses": {
          "200": {
            "description": "Coverage details",
            "content": {
              "application/json": {
                "schema": {
                  "type": "object",
                  "properties": {
                    "amount": {"type": "number"},
                    "type": {"type": "string"}
                  }
                }
              }
            }
          }
        }
      }
    },
    "/api/v1/beneficiaries": {
      "get": {
        "operationId": "getBeneficiaries_v1",
        "parameters": [
          {
            "name": "policy_id",
            "in": "query",
            "required": true,
            "schema": {"type": "string"}
          }
        ],
        "responses": {
          "200": {
            "description": "List of beneficiaries",
            "content": {
              "application/json": {
                "schema": {
                  "type": "array",
                  "items": {
                    "type": "object",
                    "properties": {
                      "beneficiary_name": {"type": "string"},
                      "relation": {"type": "string"}
                    }
                  }
                }
              }
            }
          }
        }
      }
    },
    "/api/v1/policy/search": {
      "get": {
        "operationId": "searchPolicies_v1",
        "parameters": [
          {
            "name": "customer_id",
            "in": "query",
            "schema": {"type": "string"}
          },
          {
            "name": "type",
            "in": "query",
            "schema": {"type": "string"}
          },
          {
            "name": "status",
            "in": "query",
            "schema": {"type": "string"}
          }
        ],
        "responses": {
          "200": {
            "description": "Matching policies",
            "content": {
              "application/json": {
                "schema": {
                  "type": "array",
                  "items": {
                    "type": "object",
                    "properties": {
                      "policy_num": {"type": "string"},
                      "policy_type": {"type": "string"}
                    }
                  }
                }
              }
            }
          }
        }
      }
    }
  }
}